bigbuy/__init__.py
bigbuy/api.py
bigbuy/exceptions.py
bigbuy/py.typed
bigbuy/rate_limit.py
bigbuy/types.py
bigbuy/version.py
pybigbuy-3.25.0.dist-info/METADATA
pybigbuy-3.25.0.dist-info/WHEEL
pybigbuy-3.25.0.dist-info/licenses/LICENSE
pybigbuy-3.25.0.dist-info/RECORD
