Metadata-Version: 2.4
Name: pybigbuy
Version: 3.25.0
Summary: BigBuy API client in Python
License: MIT
License-File: LICENSE
Author: Bixoto
Author-email: tech@bixoto.com
Requires-Python: >=3.9,<4.0
Classifier: Development Status :: 5 - Production/Stable
Classifier: License :: OSI Approved :: MIT License
Classifier: Programming Language :: Python :: 3
Classifier: Programming Language :: Python :: 3.9
Classifier: Programming Language :: Python :: 3.10
Classifier: Programming Language :: Python :: 3.11
Classifier: Programming Language :: Python :: 3.12
Classifier: Programming Language :: Python :: 3.13
Classifier: Programming Language :: Python :: 3.14
Requires-Dist: api-session (>=1.4.1,<2.0.0)
Requires-Dist: requests (>=2.25.1,<3.0.0)
